ZCTransNet/ATFC.cp311-win_amd64.pyd
ZCTransNet/__init__.py
ZCTransNet-0.1.4.dist-info/METADATA
ZCTransNet-0.1.4.dist-info/WHEEL
ZCTransNet-0.1.4.dist-info/top_level.txt
ZCTransNet-0.1.4.dist-info/RECORD
